{"status":0,"id":"010c75b762e1b05674aed6b32bc3eeca-1","hypotheses":[{"utterance":"publication use it as a decent to look up lines are stunningly good","confidence":0.7997485},{"utterance":"Plantation use it as a decent to look up lines are stunningly good"},{"utterance":"publication use it as a decent to look up times a stunningly good"},{"utterance":"Plantation use it as a decent to look up times a stunningly good"},{"utterance":"PlayStation use it as a decent to look up lines are stunningly good"},{"utterance":"police station use it as a decent to look up lines are stunningly good"},{"utterance":"PlayStation use it as a decent to look up times a stunningly good"},{"utterance":"police station use it as a decent to look up times a stunningly good"},{"utterance":"publication use it as a decent to look up lines of stunningly good"},{"utterance":"Plantation use it as a decent to look up lines of stunningly good"}]}
