{"status":0,"id":"60090984f5a638d8c04f981e50a5726b-1","hypotheses":[{"utterance":"so I can have a bunch of things to buy some function and then return a map of the thing","confidence":0.8720783},{"utterance":"so I can have a bunch of things to buy some functions and then return a map of the thing"},{"utterance":"so I can have a bunch of things to buy some function and then return a map of the things"},{"utterance":"so I can have a bunch of things to buy some function and then return a map of the saying"},{"utterance":"so I can have a bunch of things to buy some functions and then return a map of the things"},{"utterance":"so I can have a bunch of things to buy some functions and then return a map of the saying"},{"utterance":"so I can have a bunch of things to buy some function and then return a map of the things too"},{"utterance":"so I can have a bunch of things to buy some functions and then return a map of the things too"},{"utterance":"so I can have a bunch of things to buy some function and then return a map of the things to do"},{"utterance":"so I can have a bunch of things to buy some functions and then return a map of the things to do"}]}
