{"status":0,"id":"49bfa32f0d901efc7aee3f512ad2408d-1","hypotheses":[{"utterance":"I'm how to get it there to test it next time um and uh","confidence":0.9625698},{"utterance":"um how to get it there to test it next time um and uh"},{"utterance":"umm how to get it there to test it next time um and uh"},{"utterance":"I'm how to get it there to test it next time um and uh uh"},{"utterance":"I'm how to get it there to test it next time um and uh oh"},{"utterance":"I'm how to get it there to test it next time um and uh huh"},{"utterance":"I'm how to get it there to test it next time uh and um"},{"utterance":"I'm how to get it there to test it next time um and um"},{"utterance":"um how to get it there to test it next time um and uh uh"},{"utterance":"um how to get it there to test it next time um and uh oh"}]}
