{"status":0,"id":"c93c8a9df1909b4457ce43970e526dc7-1","hypotheses":[{"utterance":"puzzle box and closer I'm calling speech vehicle into Java","confidence":0.7899265},{"utterance":"Fox and closer I'm calling speech vehicle into Java"},{"utterance":"puzzle box and closer I'm calling speech vehicle into job"},{"utterance":"puzzle box and closer I'm calling speech to the equivalent to Java"},{"utterance":"puzzle box and closer I'm calling speech to the equivalent to job"},{"utterance":"puzzle box and closer I'm calling feature vehicle into Java"},{"utterance":"Fox and closer I'm calling speech vehicle into job"},{"utterance":"Fox and closer I'm calling speech to the equivalent to Java"},{"utterance":"puzzle box and closer I'm calling speech vehicle into Job"},{"utterance":"Fox and closer I'm calling speech to the equivalent to job"}]}
