{"status":0,"id":"bfa7af267080407f69ace9c9df5cfef4-1","hypotheses":[{"utterance":"uh so I'm a talking about for the things scheduling","confidence":0.8479064},{"utterance":"uh so I'mma talking about for the things scheduling"},{"utterance":"uh so I'm a pervert about for the things scheduling"},{"utterance":"uh so I'm A talking about for the things scheduling"},{"utterance":"uh so I'm a thought about for the things scheduling"},{"utterance":"uh so I'm a talking about for the things schedule"},{"utterance":"uh so I'mma talking about for the things schedule"},{"utterance":"uh so I'm a pervert about for the things schedule"},{"utterance":"uh so I'mma about for the things scheduling"},{"utterance":"uh so I'm off talking about for the things scheduling"}]}
