{"status":0,"id":"4e7663e6918ec23ea22f41b98121ab8f-1","hypotheses":[{"utterance":"does your eye twitch compilation will find given the symbol varta with your car","confidence":0.6101306},{"utterance":"does your eye twitch compilation will find given a symbol varta with your car"},{"utterance":"does your eye twitch compilation will find given the symbol varta with your cars"},{"utterance":"does your eye twitch compilation will find given a symbol varta with your cars"},{"utterance":"does your eye twitch compilation will find given the symbol varta with your car spa"},{"utterance":"does your eye twitch compilation will find given a symbol varta with your car spa"},{"utterance":"I wish compilation will find given the symbol varta with your car"},{"utterance":"I wish compilation will find given a symbol varta with your car"},{"utterance":"does your eye twitch compilation will find given the symbol varta with the car spa"},{"utterance":"does your eye twitch compilation will find given a symbol varta with the car spa"}]}
