{"status":0,"id":"966f2ef9fa0a22724b1ae7c0b6556477-1","hypotheses":[{"utterance":"that was Walton's to it off and is your structure which means they have","confidence":0.6818013},{"utterance":"that was Walton's to it um and is your structure which means they have"},{"utterance":"that was Walton's to it um an issue structure which means they have"},{"utterance":"that was Walton's to it off and it's your structure which means they have"},{"utterance":"that was Walton's do it off and is your structure which means they have"},{"utterance":"that was Walton's to it um MSU structure which means they have"},{"utterance":"that was Walton's to it um and it's your structure which means they have"},{"utterance":"that was Walton's do it um and is your structure which means they have"},{"utterance":"that was Walton's do it um an issue structure which means they have"},{"utterance":"that was Walton's to it off and is your structure which means they have to"}]}
