{"status":0,"id":"ed5be6bddb61f129c5e34e01aa370a16-1","hypotheses":[{"utterance":"in charge of making sure that that's the case so we're going to take a location where Paso","confidence":0.8275753},{"utterance":"in charge of making sure that that's the case so we're going to take a location where Pasadena"},{"utterance":"in charge of making sure that that's the case so we're going to take a location will pass away"},{"utterance":"in charge of making sure that that's the case so we're going to take a location for Passover"},{"utterance":"in charge of making sure that that's the case so we're going to take a location where pass away"},{"utterance":"in charge of making sure that that's the case so we're going to take a location where password"},{"utterance":"in charge of making sure that that's the case so we're going to take the location where Paso"},{"utterance":"in charge of making sure that that's the case so we're going to take the location where Pasadena"},{"utterance":"in charge of making sure that that's the case so we're going to take a location for Paso"},{"utterance":"in charge of making sure that that's the case so we're going to take a location for Pasadena"}]}
