{"status":0,"id":"deba2d53254b56c7642f585568a90d52-1","hypotheses":[{"utterance":"is this a while running on buildings instantly you","confidence":0.7592666},{"utterance":"is this a while running off building instantly you"},{"utterance":"is this a while running ability instantly you"},{"utterance":"is this a while running on buildings instantly use"},{"utterance":"is this a while running off building instantly use"},{"utterance":"is this a while running on buildings instantly news"},{"utterance":"is this a while running off building instantly news"},{"utterance":"is this a while running ability instantly use"},{"utterance":"is this a while running on buildings instantly News"},{"utterance":"is this a while running off building instantly News"}]}
