{"status":0,"id":"ca35fa79fca3c9c7a32a359907556e02-1","hypotheses":[{"utterance":"work we get the work of old P worry we were removed from this place","confidence":0.8449081},{"utterance":"work we get the book called old P worry we were removed from this place"},{"utterance":"work we get the work of old to worry we were removed from this place"},{"utterance":"work we get the book called old to worry we were removed from this place"},{"utterance":"work we get the work of old pee worry we were removed from this place"},{"utterance":"work we get the book called old pee worry we were removed from this place"},{"utterance":"work we get the world old P worry we were removed from this place"},{"utterance":"work we get the world old to worry we were removed from this place"},{"utterance":"work we get the work of old P worry we were removed from the place"},{"utterance":"work we get the book called old P worry we were removed from the place"}]}
